certbot_freenas_deployer/__init__.py
certbot_freenas_deployer/__main__.py
certbot_freenas_deployer/certbot_freenas_deployer.py
certbot_freenas_deployer/cli.py
certbot_freenas_deployer-1.1.1.dist-info/AUTHORS.rst
certbot_freenas_deployer-1.1.1.dist-info/LICENSE
certbot_freenas_deployer-1.1.1.dist-info/METADATA
certbot_freenas_deployer-1.1.1.dist-info/WHEEL
certbot_freenas_deployer-1.1.1.dist-info/entry_points.txt
certbot_freenas_deployer-1.1.1.dist-info/top_level.txt
certbot_freenas_deployer-1.1.1.dist-info/RECORD
