Metadata-Version: 2.1
Name: certbot-freenas-deployer
Version: 1.1.1
Summary: A simple tool to deploy TLS certificates obtained using Certbot to FreeNAS systems.
Home-page: https://github.com/kpfleming/certbot_freenas_deployer
Author: Kevin P. Fleming
Author-email: kevin+py@km6g.us
License: Apache Software License 2.0
Keywords: certbot freenas
Platform: UNKNOWN
Classifier: Development Status :: 5 - Production/Stable
Classifier: Intended Audience :: Developers
Classifier: License :: OSI Approved :: Apache Software License
Classifier: Natural Language :: English
Classifier: Programming Language :: Python :: 3.5
Classifier: Programming Language :: Python :: 3.6
Classifier: Environment :: Console
Classifier: Operating System :: OS Independent
Classifier: Topic :: System :: Systems Administration
Requires-Python: >=3.5
Requires-Dist: click (>=6.0)
Requires-Dist: requests
